lib2nbdev/__init__.py
lib2nbdev/_nbdev.py
lib2nbdev/convert.py
lib2nbdev/generators.py
lib2nbdev-1.0.0.dist-info/LICENSE
lib2nbdev-1.0.0.dist-info/METADATA
lib2nbdev-1.0.0.dist-info/WHEEL
lib2nbdev-1.0.0.dist-info/entry_points.txt
lib2nbdev-1.0.0.dist-info/top_level.txt
lib2nbdev-1.0.0.dist-info/RECORD
