Metadata-Version: 2.1
Name: lib2nbdev
Version: 1.0.0
Summary: A small library for converting existing libraries and projects to nbdev
Home-page: https://github.com/Novetta/lib2nbdev/tree/main/
Author: Zachary Mueller
Author-email: zmueller@novetta.com
License: Apache Software License 2.0
Keywords: nbdev lib2nbdev fastai fastcore Novetta
Platform: UNKNOWN
Classifier: Development Status :: 6 - Mature
Classifier: Intended Audience :: Developers
Classifier: Natural Language :: English
Classifier: Programming Language :: Python :: 3.6
Classifier: Programming Language :: Python :: 3.7
Classifier: Programming Language :: Python :: 3.8
Classifier: License :: OSI Approved :: Apache Software License
Requires-Python: >=3.6
License-File: LICENSE
Requires-Dist: nbdev (<=1.1.23,>1.1.15)
Requires-Dist: fastprogress (==1.0.0)
Requires-Dist: fastcore (<=1.3.27,>=1.3.21)
Requires-Dist: requests (<=2.26.0,>=2.25.1)
